fast_requests/__init__.py
fast_requests/fast_requests.py
fast_requests/fast_requetst_cpp.pyd
fast_requests/libcurl.dll
fast_requests/zlib1.dll
requests_cpp-0.1.0.dist-info/METADATA
requests_cpp-0.1.0.dist-info/WHEEL
requests_cpp-0.1.0.dist-info/top_level.txt
requests_cpp-0.1.0.dist-info/RECORD
