Metadata-Version: 2.1
Name: requests-cpp
Version: 0.1.0
Summary: Use c ++ multi-threaded http request library
Home-page: https://github.com/daimiaopeng/fast_requests
Author: daimiaopeng
Author-email: daimiaopeng@qq.com
License: MIT Licence
Keywords: pip,requests,cpr,pybind11
Platform: UNKNOWN
Classifier: Programming Language :: Python :: 3
Classifier: License :: OSI Approved :: MIT License
Classifier: Operating System :: OS Independent
